pysmeter/__init__.py
pysmeter/common.py
pysmeter/download_model.py
pysmeter/model.py
pysmeter-1.0.1.data/scripts/pysmeter
pysmeter-1.0.1.dist-info/LICENSE
pysmeter-1.0.1.dist-info/METADATA
pysmeter-1.0.1.dist-info/NOTICE
pysmeter-1.0.1.dist-info/WHEEL
pysmeter-1.0.1.dist-info/top_level.txt
pysmeter-1.0.1.dist-info/RECORD
