Metadata-Version: 2.1
Name: pysmeter
Version: 1.0.1
Summary: A package for predicting the HTC of a building using smart meter data.
Home-page: https://github.com/cse-bristol/pysmeter
Author: Mark Gibbons
Author-email: mark.gibbons@cse.org.uk
License: UNKNOWN
Platform: UNKNOWN
Classifier: Programming Language :: Python :: 3
Classifier: License :: OSI Approved :: Apache Software License
Classifier: Operating System :: OS Independent
Requires-Python: >=3.6
Requires-Dist: tensorflow (<2)
Requires-Dist: numpy
Requires-Dist: requests
